maildir2mbox.py
maildir2mbox-1.0.dist-info/LICENSE.txt
maildir2mbox-1.0.dist-info/METADATA
maildir2mbox-1.0.dist-info/WHEEL
maildir2mbox-1.0.dist-info/top_level.txt
maildir2mbox-1.0.dist-info/RECORD
