Metadata-Version: 2.1
Name: maildir2mbox
Version: 1.0
Summary: Conversion of a mailbox in the maildir format to the mbox format
Home-page: https://github.com/bluebird75/maildir2mbox
Author: Philippe Fremy
Author-email: phil.fremy@free.fr
License: Public Domain
Keywords: maildir mbox
Platform: UNKNOWN
Classifier: Topic :: Communications :: Email
Classifier: License :: Public Domain
Classifier: Operating System :: OS Independent
Classifier: Development Status :: 5 - Production/Stable
Classifier: Programming Language :: Python :: 3
Classifier: Topic :: Utilities
Requires-Python: >=3.5
